{
	"XResolution": 72,
	"YResolution": 72,
	"YCbCrPositioning": 1,
	"ImageDescription": "S/W Ver: 98.50.11R",
	"Make": "MOTOROLA",
	"Model": "RAZRV6vc",
	"ModifyDate": "2010:02:27 11:05:15",
	"ExifOffset": 346,
	"Compression": 6,
	"ThumbnailOffset": 520,
	"ThumbnailLength": 2033,
	"ImageWidth": 128,
	"ImageHeight": 160,
	"ExifVersion": "2.1",
	"FlashpixVersion": "NaN",
	"ExifImageWidth": 1200,
	"ExifImageHeight": 1600,
	"DateTimeOriginal": "2010:02:27 11:05:15",
	"CreateDate": "2010:02:27 11:05:15",
	"ExposureCompensation": 0
}