{
	"Make": "Nokia",
	"Model": "7510 Supernova",
	"XResolution": 300,
	"YResolution": 300,
	"ResolutionUnit": 2,
	"Software": "V 06.65",
	"YCbCrPositioning": 1,
	"ExifOffset": 224,
	"CustomRendered": 0,
	"ExposureMode": 0,
	"WhiteBalance": 0,
	"DigitalZoomRatio": 1,
	"SceneCaptureType": 0,
	"Compression": 6,
	"ThumbnailOffset": 460,
	"ThumbnailLength": 4442,
	"DateTimeOriginal": "2010:04:22 18:49:57",
	"CreateDate": "2010:04:22 18:49:57",
	"ColorSpace": 1,
	"ExifImageWidth": 1600,
	"ExifImageHeight": 1200
}