{
	"CFAPattern": "0,2,0,2,1,2,0,1",
	"ColorSpace": "sRGB",
	"ComponentsConfiguration": "Y, Cb, Cr, -",
	"CompressedBitsPerPixel": "4",
	"Contrast": "Normal",
	"CreateDate": "2011:01:13 21:38:18",
	"CustomRendered": "Normal",
	"DateTimeOriginal": "2011:01:13 21:38:18",
	"DigitalZoomRatio": "1",
	"ExifIFDPointer": "216",
	"ExifImageHeight": "2592",
	"ExifImageWidth": "3872",
	"ExifVersion": "0221",
	"ExposureBias": "0",
	"ExposureMode": "0",
	"ExposureProgram": "Not defined",
	"ExposureTime": "0.016666666666666666",
	"FNumber": "5.6",
	"FileSource": "DSC",
	"Flash": "Flash fired, auto mode, return light detected",
	"FlashpixVersion": "0100",
	"FocalLength": "55 mm",
	"FocalLengthIn35mmFilm": "82",
	"GainControl": "None",
	"ISO": "200",
	"InteroperabilityIFDPointer": "27184",
	"LightSource": "",
	"Make": "NIKON CORPORATION",
	"MakerNoteIFDPointer": "852",
	"MaxApertureValue": "5",
	"MeteringMode": "Pattern",
	"Model": "NIKON D60",
	"ModifyDate": "2011:01:13 21:38:18",
	"Orientation": "1",
	"ResolutionUnit": "2",
	"Saturation": "Normal",
	"SceneCaptureType": "Standard",
	"SceneType": "Directly photographed",
	"SensingMethod": "One-chip color area sensor",
	"SerialNumber": "3323685",
	"Sharpness": "Normal",
	"Software": "Ver.1.01",
	"SubjectDistanceRange": "",
	"SubsecTime": "10",
	"SubsecTimeDigitized": "10",
	"SubsecTimeOriginal": "10",
	"UserComment": "792",
	"WhiteBalance": "Auto",
	"XResolution": "300",
	"YCbCrPositioning": "2",
	"YResolution": "300"
}