{
	"ApertureValue": "3.852",
	"ColorSpace": "sRGB",
	"ComponentsConfiguration": "Y, Cb, Cr, -",
	"CompressedBitsPerPixel": "2",
	"Copyright": "Copyright 2007",
	"CreateDate": "2010:05:01 14:45:02",
	"DateTimeOriginal": "2010:05:01 14:45:02",
	"DigitalZoomRatio": "1",
	"ExifIFDPointer": "292",
	"ExifImageHeight": "2448",
	"ExifImageWidth": "3264",
	"ExifVersion": "0220",
	"ExposureBias": "0",
	"ExposureMode": "0",
	"ExposureProgram": "Normal program",
	"ExposureTime": "0.008",
	"FNumber": "3.8",
	"FileSource": "DSC",
	"Flash": "Flash fired, compulsory flash mode, return light not detected",
	"FlashpixVersion": "0100",
	"FocalLength": "10.7 mm",
	"FocalLengthIn35mmFilm": "64438",
	"ISO": "50",
	"ImageDescription": "D:\\DCIM\\100DICAM\\DSCI1921.JPG",
	"InteroperabilityIFDPointer": "3742",
	"LightSource": "",
	"Make": "PENTACONLM 8203x.0",
	"MakerNoteIFDPointer": "1064",
	"MaxApertureValue": "2.866",
	"MeteringMode": "MultiSpot",
	"Model": "LM 8203x.04xCo",
	"ModifyDate": "2010:05:01 14:46:27",
	"Orientation": "0",
	"RelatedSoundFile": "",
	"ResolutionUnit": "2",
	"SceneCaptureType": "Portrait",
	"SceneType": "Directly photographed",
	"ShutterSpeedValue": "6.966",
	"Software": "1.100",
	"UserComment": "770",
	"WhiteBalance": "Auto",
	"XResolution": "96",
	"YCbCrPositioning": "2",
	"YResolution": "96"
}