{
	"ColorSpace": "sRGB",
	"ComponentsConfiguration": "Y, Cb, Cr, -",
	"DateTime": "2000:02:08 10:54:52",
	"DateTimeDigitized": "2000:02:08 10:54:52",
	"DateTimeOriginal": "2000:02:08 10:54:52",
	"ExifIFDPointer": "302",
	"ExifVersion": "0220",
	"FlashpixVersion": "0100",
	"ImageDescription": "",
	"InteroperabilityIFDPointer": "612",
	"Make": "Sony Ericsson",
	"Model": "Z530i",
	"Orientation": "1",
	"PixelXDimension": "0",
	"PixelYDimension": "0",
	"ResolutionUnit": "2",
	"Software": "R6AC001     prgCXC1250454GENERICM 2.3",
	"XResolution": "72",
	"YCbCrPositioning": "2",
	"YResolution": "72"
}