{
	"BrightnessValue": "6.62",
	"ColorSpace": "sRGB",
	"ComponentsConfiguration": "Y, Cb, Cr, -",
	"CompressedBitsPerPixel": "2",
	"Contrast": "Normal",
	"CreateDate": "2010:05:03 07:58:41",
	"CustomRendered": "Normal",
	"DateTimeOriginal": "2010:05:03 07:58:41",
	"ExifIFDPointer": "374",
	"ExifImageHeight": "1520",
	"ExifImageWidth": "2288",
	"ExifVersion": "0230",
	"ExposureBias": "0",
	"ExposureMode": "1",
	"ExposureProgram": "Manual",
	"ExposureTime": "0.0125",
	"FNumber": "5.6",
	"FileSource": "DSC",
	"Flash": "Flash did not fire, compulsory flash mode",
	"FlashpixVersion": "0100",
	"FocalLength": "70 mm",
	"FocalLengthIn35mmFilm": "105",
	"ISO": "200",
	"ImageDescription": "SONY DSC",
	"InteroperabilityIFDPointer": "43600",
	"LightSource": "",
	"Make": "SONY",
	"MakerNoteIFDPointer": "920",
	"MaxApertureValue": "3",
	"MeteringMode": "Pattern",
	"Model": "NEX-5",
	"ModifyDate": "2010:05:03 07:58:41",
	"Orientation": "1",
	"ResolutionUnit": "2",
	"Saturation": "Normal",
	"SceneCaptureType": "Standard",
	"SceneType": "Directly photographed",
	"Sharpness": "Normal",
	"Software": "NEX-5 v1.00",
	"UserComment": "43484",
	"WhiteBalance": "Manual",
	"XResolution": "350",
	"YCbCrPositioning": "2",
	"YResolution": "350"
}