{
	"ColorSpace": "sRGB",
	"ComponentsConfiguration": "Y, Cb, Cr, -",
	"CompressedBitsPerPixel": "2",
	"Contrast": "Normal",
	"CreateDate": "2008:08:14 14:15:03",
	"CustomRendered": "Normal",
	"DateTimeOriginal": "2008:08:14 14:15:03",
	"DigitalZoomRatio": "0",
	"ExifIFDPointer": "570",
	"ExifImageHeight": "3000",
	"ExifImageWidth": "4000",
	"ExifVersion": "0221",
	"ExposureBias": "-0.33",
	"ExposureMode": "0",
	"ExposureProgram": "Normal program",
	"ExposureTime": "0.0025",
	"FNumber": "13",
	"FileSource": "DSC",
	"Flash": "Flash did not fire, compulsory flash mode",
	"FlashpixVersion": "0100",
	"FocalLength": "31 mm",
	"FocalLengthIn35mmFilm": "62",
	"GainControl": "None",
	"ISO": "100",
	"InternalSerialNumber": "(F91) 2008:07:11 no. 0033",
	"InteroperabilityIFDPointer": "8332",
	"LightSource": "Fine weather",
	"Make": "Panasonic",
	"MakerNoteIFDPointer": "1072",
	"MaxApertureValue": "4.86",
	"MeteringMode": "Pattern",
	"Model": "DMC-G1",
	"ModifyDate": "2008:08:14 14:15:03",
	"Orientation": "1",
	"ResolutionUnit": "2",
	"Saturation": "Normal",
	"SceneCaptureType": "Standard",
	"SceneType": "Directly photographed",
	"SensingMethod": "One-chip color area sensor",
	"Sharpness": "Normal",
	"Software": "Ver.0.3",
	"WhiteBalance": "Manual",
	"XResolution": "180",
	"YCbCrPositioning": "2",
	"YResolution": "180"
}