{
	"ApertureValue": "3",
	"BrightnessValue": "3.16",
	"ColorSpace": "sRGB",
	"ComponentsConfiguration": "Y, Cb, Cr, -",
	"CompressedBitsPerPixel": "2",
	"Copyright": "",
	"CreateDate": "2004:02:05 21:25:24",
	"DateTimeOriginal": "2004:02:05 21:25:24",
	"ExifIFDPointer": "246",
	"ExifImageHeight": "960",
	"ExifImageWidth": "1280",
	"ExifVersion": "0210",
	"ExposureBias": "0",
	"ExposureProgram": "Normal program",
	"FNumber": "2.8",
	"FileSource": "DSC",
	"Flash": "No Flash",
	"FlashpixVersion": "0100",
	"FocalLength": "8.7 mm",
	"FocalPlaneResolutionUnit": "3",
	"FocalPlaneXResolution": "1270",
	"FocalPlaneYResolution": "1270",
	"ISO": "200",
	"InteroperabilityIFDPointer": "922",
	"Make": "FUJIFILM",
	"MakerNoteIFDPointer": "708",
	"MaxApertureValue": "3",
	"MeteringMode": "Pattern",
	"Model": "DS-270HD",
	"ModifyDate": "2004:02:05 21:25:24",
	"Orientation": "1",
	"ResolutionUnit": "2",
	"SceneType": "Directly photographed",
	"SensingMethod": "One-chip color area sensor",
	"ShutterSpeedValue": "5.7",
	"Software": "Digital Camera DS-270HD Ver1.0;",
	"XResolution": "72",
	"YCbCrPositioning": "2",
	"YResolution": "72"
}