{
	"BrightnessValue": "3.6",
	"ColorSpace": "sRGB",
	"ComponentsConfiguration": "Y, Cb, Cr, -",
	"Contrast": "Normal",
	"CustomRendered": "Normal",
	"DateTime": "2005:12:16 03:13:55",
	"DateTimeDigitized": "2005:12:16 03:13:55",
	"DateTimeOriginal": "2005:12:16 03:13:55",
	"DigitalZoomRatio": "0",
	"ExifIFDPointer": "404",
	"ExifVersion": "0220",
	"ExposureBias": "0",
	"ExposureMode": "0",
	"ExposureProgram": "Normal program",
	"ExposureTime": "0.016666666666666666",
	"FNumber": "3.2",
	"Flash": "Flash fired, auto mode",
	"FlashpixVersion": "0100",
	"FocalLength": "8.9 mm",
	"FocalLengthIn35mmFilm": "68",
	"GainControl": "High gain up",
	"ISOSpeedRatings": "200",
	"ImageDescription": "KONICA MINOLTA DIGITAL CAMERA",
	"InteroperabilityIFDPointer": "15956",
	"LightSource": "",
	"Make": "Konica Minolta Camera, Inc.",
	"MakerNoteIFDPointer": "986",
	"MaxApertureValue": "3.4",
	"MeteringMode": "Pattern",
	"Model": "DiMAGE X21",
	"Orientation": "1",
	"PixelXDimension": "1600",
	"PixelYDimension": "1200",
	"ResolutionUnit": "2",
	"Saturation": "Normal",
	"SceneCaptureType": "Standard",
	"Sharpness": "Normal",
	"Software": "DiMAGE X21 Ver1.00",
	"SubjectArea": "800,600,260,260",
	"SubjectDistanceRange": "",
	"UserComment": "914",
	"WhiteBalance": "Auto",
	"XResolution": "72",
	"YCbCrPositioning": "1",
	"YResolution": "72"
}