{
	"ColorSpace": "sRGB",
	"ComponentsConfiguration": "Y, Cb, Cr, -",
	"CompressedBitsPerPixel": "4.705882352941177",
	"Contrast": "Normal",
	"CreateDate": "2007:09:18 16:16:28",
	"CustomRendered": "Normal",
	"DateTimeOriginal": "2007:09:18 16:16:28",
	"DigitalZoomRatio": "NaN",
	"ExifIFDPointer": "282",
	"ExifImageHeight": "2448",
	"ExifImageWidth": "3264",
	"ExifVersion": "0221",
	"ExposureBias": "0.6666666666666666",
	"ExposureMode": "1",
	"ExposureProgram": "Normal program",
	"ExposureTime": "0.07692307692307693",
	"FNumber": "4.5",
	"FileSource": "DSC",
	"Flash": "Flash did not fire, compulsory flash mode",
	"FlashpixVersion": "0100",
	"FocalLength": "12.47 mm",
	"FocalLengthIn35mmFilm": "71",
	"GainControl": "None",
	"ISO": "50",
	"InteroperabilityIFDPointer": "34050",
	"LightSource": "",
	"Make": "CASIO COMPUTER CO.,LTD.",
	"MakerNoteIFDPointer": "768",
	"MaxApertureValue": "3.3",
	"MeteringMode": "CenterWeightedAverage",
	"Model": "EX-Z8",
	"ModifyDate": "2007:09:18 16:16:28",
	"Orientation": "1",
	"ResolutionUnit": "2",
	"Saturation": "Normal",
	"SceneCaptureType": "Portrait",
	"Sharpness": "Normal",
	"Software": "1.00",
	"WhiteBalance": "Auto",
	"XResolution": "72",
	"YCbCrPositioning": "1",
	"YResolution": "72"
}