{
	"ColorSpace": "sRGB",
	"ComponentsConfiguration": "Y, Cb, Cr, -",
	"CustomRendered": "Normal",
	"DateTimeDigitized": "2008:01:04 03:23:28",
	"DateTimeOriginal": "2008:01:04 03:23:28",
	"DigitalZoomRatio": "1",
	"ExifIFDPointer": "144",
	"ExifVersion": "0220",
	"ExposureMode": "0",
	"ExposureTime": "0.047619047619047616",
	"Flash": "No Flash",
	"FlashpixVersion": "0100",
	"InteroperabilityIFDPointer": "410",
	"Make": "SAMSUNG",
	"Model": "SCH-V730",
	"Orientation": "1",
	"PixelXDimension": "1152",
	"PixelYDimension": "864",
	"ResolutionUnit": "2",
	"SceneCaptureType": "Standard",
	"SubjectDistanceRange": "",
	"WhiteBalance": "Manual",
	"XResolution": "72",
	"YCbCrPositioning": "1",
	"YResolution": "72"
}