{
	"ColorSpace": "sRGB",
	"ComponentsConfiguration": "Y, Cb, Cr, -",
	"CreateDate": "2009:08:22 16:09:13",
	"CustomRendered": "Normal",
	"DateTimeOriginal": "2009:08:22 16:09:13",
	"DigitalZoomRatio": "0",
	"ExifIFDPointer": "212",
	"ExifImageHeight": "480",
	"ExifImageWidth": "640",
	"ExifVersion": "0220",
	"ExposureMode": "0",
	"ExposureTime": "0.008",
	"Flash": "Flash fired",
	"FlashpixVersion": "0100",
	"InteroperabilityIFDPointer": "546",
	"Make": "SAMSUNG",
	"Model": "SCH-V890",
	"Orientation": "1",
	"ResolutionUnit": "2",
	"SceneCaptureType": "Standard",
	"Software": "M6550B-SNAAR-30303",
	"SubjectDistanceRange": "",
	"WhiteBalance": "Auto",
	"XResolution": "72",
	"YCbCrPositioning": "1",
	"YResolution": "72"
}