{
	"Make": "LG CYON",
	"Model": "SU950",
	"Orientation": 1,
	"XResolution": 72,
	"YResolution": 72,
	"ResolutionUnit": 2,
	"Software": "LG Electronics     ",
	"YCbCrPositioning": 1,
	"ExifOffset": 184,
	"GPSInfo": 924,
	"Compression": 6,
	"ThumbnailOffset": 1196,
	"ThumbnailLength": 29046,
	"ExposureTime": 0.001597444089456869,
	"FNumber": 2.7890625,
	"ExposureProgram": 2,
	"ISO": 50,
	"DateTimeOriginal": "1980:01:23 02:25:47",
	"CreateDate": "1980:01:23 02:25:47",
	"ShutterSpeedValue": 9.29,
	"ApertureValue": 2.97,
	"BrightnessValue": 8.26,
	"ExposureCompensation": 0,
	"MaxApertureValue": 2.97,
	"MeteringMode": 255,
	"LightSource": 0,
	"Flash": 32,
	"FocalLength": 3.67,
	"ColorSpace": 1,
	"ExifImageWidth": 2560,
	"ExifImageHeight": 1920,
	"InteropOffset": 1070,
	"SensingMethod": 2,
	"CustomRendered": 0,
	"ExposureMode": 0,
	"WhiteBalance": 0,
	"DigitalZoomRatio": null,
	"FocalLengthIn35mmFormat": 0,
	"SceneCaptureType": 1,
	"Contrast": 0,
	"Saturation": 0,
	"Sharpness": 0,
	"GPSVersionID": [
		2,
		2,
		0,
		0
	],
	"GPSLatitudeRef": "N",
	"GPSLatitude": [
		0,
		0,
		0
	],
	"GPSLongitudeRef": "E",
	"GPSLongitude": [
		0,
		0,
		0
	],
	"GPSAltitudeRef": 0,
	"GPSAltitude": 0,
	"InteropIndex": "R98",
	"error": "Unable to extract Makernote information as it is in an unsupported or unrecognized format."
}