{
	"img": "sampleImages/Panasonic/PanasonicDMC-FZ8.jpg",
	"exifJS": {
		"ColorSpace": "sRGB",
		"ComponentsConfiguration": "Y, Cb, Cr, -",
		"CompressedBitsPerPixel": "2",
		"Contrast": "Normal",
		"CustomRendered": "Normal",
		"DateTime": "2007:01:06 15:07:29",
		"DateTimeDigitized": "2007:01:06 15:07:29",
		"DateTimeOriginal": "2007:01:06 15:07:29",
		"DigitalZoomRatio": "0",
		"ExifIFDPointer": "418",
		"ExifVersion": "0221",
		"ExposureBias": "0",
		"ExposureMode": "0",
		"ExposureProgram": "Aperture priority",
		"ExposureTime": "0.003125",
		"FNumber": "5.6",
		"FileSource": "DSC",
		"Flash": "Flash did not fire, compulsory flash mode",
		"FlashpixVersion": "0100",
		"FocalLength": "9.5 mm",
		"FocalLengthIn35mmFilm": "57",
		"GainControl": "None",
		"ISOSpeedRatings": "100",
		"InternalSerialNumber": "(S04) 2006:12:05 no. 0024",
		"InteroperabilityIFDPointer": "7714",
		"LightSource": "",
		"Make": "Panasonic",
		"MakerNoteIFDPointer": "920",
		"MaxApertureValue": "3",
		"MeteringMode": "Spot",
		"Model": "DMC-FZ8",
		"Orientation": "8",
		"PixelXDimension": "3072",
		"PixelYDimension": "2304",
		"ResolutionUnit": "2",
		"Saturation": "Normal",
		"SceneCaptureType": "Standard",
		"SceneType": "Directly photographed",
		"SensingMethod": "One-chip color area sensor",
		"Sharpness": "Normal",
		"Software": "Ver.1.0",
		"WhiteBalance": "Auto",
		"XResolution": "72",
		"YCbCrPositioning": "2",
		"YResolution": "72"
	},
	"exifGomfunkel": {
		"AFAreaMode": [
			16,
			0
		],
		"AFAssistLamp": 4,
		"Audio": 2,
		"BabyAge": "£¤¥¦§¨©ª²³´µ¶·¸¹ºÂÃÄ",
		"BurstMode": 0,
		"ColorEffect": 1,
		"ColorMode": 0,
		"ColorSpace": 1,
		"CompressedBitsPerPixel": 2,
		"Compression": 6,
		"Contrast": 0,
		"ContrastMode": 0,
		"ConversionLens": 4,
		"CreateDate": "2007:01:06 15:07:29",
		"CustomRendered": 0,
		"DateTimeOriginal": "2007:01:06 15:07:29",
		"DigitalZoomRatio": 0,
		"ExifImageHeight": 2304,
		"ExifImageWidth": 3072,
		"ExifOffset": 418,
		"ExposureCompensation": 0,
		"ExposureMode": 0,
		"ExposureProgram": 3,
		"ExposureTime": 0.003125,
		"FNumber": 5.6,
		"Flash": 16,
		"FlashBias": 0,
		"FlashFired": 1,
		"FocalLength": 9.5,
		"FocalLengthIn35mmFormat": 57,
		"FocusMode": 1,
		"GainControl": 0,
		"ISO": 100,
		"ImageQuality": 7,
		"ImageStabilization": 4,
		"InteropIndex": "R98",
		"InteropOffset": 7714,
		"LightSource": 0,
		"MacroMode": 2,
		"Make": "Panasonic",
		"MaxApertureValue": 3,
		"MeteringMode": 3,
		"Model": "DMC-FZ8",
		"ModifyDate": "2007:01:06 15:07:29",
		"NoiseReduction": 0,
		"OpticalZoomMode": 1,
		"Orientation": 8,
		"ProgramISO": 100,
		"ResolutionUnit": 2,
		"Rotation": 8,
		"Saturation": 0,
		"SceneCaptureType": 0,
		"SceneMode": 0,
		"SelfTimer": 1,
		"SensingMethod": 2,
		"SequenceNumber": 0,
		"Sharpness": 0,
		"ShootingMode": 7,
		"Software": "Ver.1.0  ",
		"TextStamp": 1,
		"ThumbnailLength": 5178,
		"ThumbnailOffset": 8084,
		"TimeSincePowerOn": 66230,
		"TravelDay": 65535,
		"WBBlueLevel": 1885,
		"WBGreenLevel": 1054,
		"WBRedLevel": 1833,
		"WBShiftAB": 0,
		"WBShiftGM": 0,
		"WhiteBalance": 1,
		"WorldTimeLocation": 1,
		"XResolution": 72,
		"YCbCrPositioning": 2,
		"YResolution": 72
	},
	"exifPerl": {
		"AFAreaMode": "1-area",
		"AFAssistLamp": "Disabled and Not Required",
		"Aperture": 5.6,
		"Audio": "No",
		"BabyAge": "(not set)",
		"BitsPerSample": 8,
		"BlueBalance": 1.788425,
		"BurstMode": "Off",
		"CircleOfConfusion": "0.005 mm",
		"ColorComponents": 3,
		"ColorEffect": "Off",
		"ColorMode": "Normal",
		"ColorSpace": "sRGB",
		"ComponentsConfiguration": "Y, Cb, Cr, -",
		"CompressedBitsPerPixel": 2,
		"Compression": "JPEG (old-style)",
		"Contrast": "Normal",
		"ContrastMode": "Normal",
		"ConversionLens": "Macro",
		"CreateDate": "2007:01:06 15:07:29",
		"CustomRendered": "Normal",
		"DataDump": "(Binary data 6152 bytes)",
		"DateTimeOriginal": "2007:01:06 15:07:29",
		"DigitalZoomRatio": 0,
		"EncodingProcess": "Baseline DCT, Huffman coding",
		"ExifByteOrder": "Little-endian (Intel, II)",
		"ExifImageHeight": 2304,
		"ExifImageWidth": 3072,
		"ExifVersion": "0221",
		"ExposureCompensation": 0,
		"ExposureMode": "Auto",
		"ExposureProgram": "Aperture-priority AE",
		"ExposureTime": "1/320",
		"FNumber": 5.6,
		"FOV": "35.1 deg",
		"FileSource": "Digital Camera",
		"FirmwareVersion": "0.0.2.8",
		"Flash": "Off, Did not fire",
		"FlashBias": 0,
		"FlashFired": "No",
		"FlashpixVersion": "0100",
		"FocalLength": "9.5 mm",
		"FocalLength35efl": "9.5 mm (35 mm equivalent: 57.0 mm)",
		"FocalLengthIn35mmFormat": "57 mm",
		"FocusMode": "Auto",
		"GainControl": "None",
		"HyperfocalDistance": "3.22 m",
		"ISO": 100,
		"ImageHeight": 8,
		"ImageQuality": "Raw",
		"ImageSize": "8x8",
		"ImageStabilization": "On, Mode 2",
		"ImageWidth": 8,
		"InternalSerialNumber": "(S04) 2006:12:05 no. 0024",
		"InteropIndex": "R98 - DCF basic file (sRGB)",
		"InteropVersion": "0100",
		"LightSource": "Unknown",
		"LightValue": 13.3,
		"MacroMode": "Off",
		"Make": "Panasonic",
		"MakerNoteVersion": "0101",
		"MaxApertureValue": 2.8,
		"MeteringMode": "Spot",
		"Model": "DMC-FZ8",
		"ModifyDate": "2007:01:06 15:07:29",
		"NoiseReduction": "Standard",
		"OpticalZoomMode": "Standard",
		"Orientation": "Rotate 270 CW",
		"PanasonicExifVersion": "0220",
		"PrintIMVersion": "0250",
		"ProgramISO": 100,
		"RedBalance": 1.739089,
		"ResolutionUnit": "inches",
		"Rotation": "Rotate 270 CW",
		"Saturation": "Normal",
		"ScaleFactor35efl": 6,
		"SceneCaptureType": "Standard",
		"SceneMode": "Off",
		"SceneType": "Directly photographed",
		"SelfTimer": "Off",
		"SensingMethod": "One-chip color area",
		"SequenceNumber": 0,
		"Sharpness": "Normal",
		"ShootingMode": "Aperture Priority",
		"ShutterSpeed": "1/320",
		"Software": "Ver.1.0",
		"TextStamp": "Off",
		"ThumbnailImage": "(Binary data 5178 bytes)",
		"ThumbnailLength": 5178,
		"ThumbnailOffset": 8096,
		"TimeSincePowerOn": "00:11:02.29",
		"TravelDay": "n/a",
		"WBBlueLevel": 1885,
		"WBGreenLevel": 1054,
		"WBRedLevel": 1833,
		"WBShiftAB": 0,
		"WBShiftGM": 0,
		"WhiteBalance": "Auto",
		"WorldTimeLocation": "Home",
		"XResolution": 72,
		"YCbCrPositioning": "Co-sited",
		"YCbCrSubSampling": "YCbCr4:2:0 (2 2)",
		"YResolution": 72
	}
}