{
	"img": "sampleImages/Sony/SonyCLIE_PEG-NX70V.jpg",
	"exifJS": {
		"ColorSpace": "sRGB",
		"ComponentsConfiguration": "Y, Cb, Cr, -",
		"DateTime": "2002:11:30 11:33:25",
		"DateTimeDigitized": "2002:11:30 11:33:25",
		"DateTimeOriginal": "2002:11:30 11:33:25",
		"ExifIFDPointer": "214",
		"ExifVersion": "0210",
		"FlashpixVersion": "0100",
		"ImageDescription": "",
		"InteroperabilityIFDPointer": "368",
		"Make": "SONY",
		"Model": "CLIE",
		"Orientation": "6",
		"PixelXDimension": "640",
		"PixelYDimension": "480",
		"ResolutionUnit": "2",
		"XResolution": "72",
		"YCbCrPositioning": "2",
		"YResolution": "72"
	},
	"exifGomfunkel": {
		"ColorSpace": 1,
		"Compression": 6,
		"CreateDate": "2002:11:30 11:33:25",
		"DateTimeOriginal": "2002:11:30 11:33:25",
		"ExifImageHeight": 480,
		"ExifImageWidth": 640,
		"ExifOffset": 214,
		"ImageDescription": "                               ",
		"InteropIndex": "R98",
		"InteropOffset": 368,
		"Make": "SONY",
		"Model": "CLIE",
		"ModifyDate": "2002:11:30 11:33:25",
		"Orientation": 6,
		"ResolutionUnit": 2,
		"ThumbnailLength": 4285,
		"ThumbnailOffset": 504,
		"XResolution": 72,
		"YCbCrPositioning": 2,
		"YResolution": 72
	},
	"exifPerl": {
		"BitsPerSample": 8,
		"ColorComponents": 3,
		"ColorSpace": "sRGB",
		"ComponentsConfiguration": "Y, Cb, Cr, -",
		"Compression": "JPEG (old-style)",
		"CreateDate": "2002:11:30 11:33:25",
		"DateTimeOriginal": "2002:11:30 11:33:25",
		"EncodingProcess": "Baseline DCT, Huffman coding",
		"ExifByteOrder": "Little-endian (Intel, II)",
		"ExifImageHeight": 480,
		"ExifImageWidth": 640,
		"ExifVersion": "0210",
		"FlashpixVersion": "0100",
		"ImageDescription": "                               ",
		"ImageHeight": 8,
		"ImageSize": "8x8",
		"ImageWidth": 8,
		"InteropIndex": "R98 - DCF basic file (sRGB)",
		"InteropVersion": "0100",
		"Make": "SONY",
		"Model": "CLIE",
		"ModifyDate": "2002:11:30 11:33:25",
		"Orientation": "Rotate 90 CW",
		"ResolutionUnit": "inches",
		"ThumbnailImage": "(Binary data 4285 bytes)",
		"ThumbnailLength": 4285,
		"ThumbnailOffset": 516,
		"XResolution": 72,
		"YCbCrPositioning": "Co-sited",
		"YCbCrSubSampling": "YCbCr4:2:0 (2 2)",
		"YResolution": 72
	}
}