{
	"img": "sampleImages/Legend/LegendSOSHOW730.jpg",
	"exifJS": {
		"ApertureValue": "3.9",
		"ColorSpace": "sRGB",
		"ComponentsConfiguration": "Y, Cb, Cr, -",
		"DateTime": "2001:01:01 00:32:15",
		"DateTimeDigitized": "2001:01:01 00:32:15",
		"DateTimeOriginal": "2001:01:01 00:32:15",
		"ExifIFDPointer": "246",
		"ExifVersion": "0210",
		"ExposureBias": "0",
		"ExposureProgram": "Landscape mode",
		"ExposureTime": "0.07142857142857142",
		"FNumber": "3.9",
		"FileSource": "DSC",
		"Flash": "No Flash",
		"FlashpixVersion": "0100",
		"ISOSpeedRatings": "100",
		"ImageDescription": "Exif JPEG",
		"InteroperabilityIFDPointer": "704",
		"LightSource": "",
		"Make": "LEGEND",
		"MakerNoteIFDPointer": "604",
		"MaxApertureValue": "3.1",
		"MeteringMode": "Pattern",
		"Model": "SOSHOW730",
		"Orientation": "1",
		"PixelXDimension": "2048",
		"PixelYDimension": "1536",
		"ResolutionUnit": "2",
		"ShutterSpeedValue": "3.8",
		"Software": "SOSHOW730  V1.00",
		"XResolution": "72",
		"YCbCrPositioning": "2",
		"YResolution": "72"
	},
	"exifGomfunkel": {
		"ApertureValue": 3.9,
		"ColorSpace": 1,
		"Compression": 6,
		"CreateDate": "2001:01:01 00:32:15",
		"DateTimeOriginal": "2001:01:01 00:32:15",
		"ExifImageHeight": 1536,
		"ExifImageWidth": 2048,
		"ExifOffset": 246,
		"ExposureCompensation": 0,
		"ExposureProgram": 8,
		"ExposureTime": 0.07142857142857142,
		"FNumber": 3.9,
		"Flash": 0,
		"ISO": 100,
		"ImageDescription": "Exif JPEG",
		"InteropIndex": "R98",
		"InteropOffset": 704,
		"LightSource": 0,
		"Make": "LEGEND         ",
		"MaxApertureValue": 3.1,
		"MeteringMode": 5,
		"Model": "SOSHOW730      ",
		"ModifyDate": "2001:01:01 00:32:15",
		"Orientation": 1,
		"ResolutionUnit": 2,
		"ShutterSpeedValue": 3.8,
		"Software": "SOSHOW730  V1.00     ",
		"ThumbnailLength": 5820,
		"ThumbnailOffset": 852,
		"XResolution": 72,
		"YCbCrPositioning": 2,
		"YResolution": 72,
		"error": "Unable to extract Makernote information as it is in an unsupported or unrecognized format."
	},
	"exifPerl": {
		"Aperture": 3.9,
		"ApertureValue": 3.9,
		"BitsPerSample": 8,
		"ColorComponents": 3,
		"ColorSpace": "sRGB",
		"ComponentsConfiguration": "Y, Cb, Cr, -",
		"Compression": "JPEG (old-style)",
		"CreateDate": "2001:01:01 00:32:15",
		"DateTimeOriginal": "2001:01:01 00:32:15",
		"EncodingProcess": "Baseline DCT, Huffman coding",
		"ExifByteOrder": "Little-endian (Intel, II)",
		"ExifImageHeight": 1536,
		"ExifImageWidth": 2048,
		"ExifVersion": "0210",
		"ExposureCompensation": 0,
		"ExposureProgram": "Landscape",
		"ExposureTime": "1/14",
		"FNumber": 3.9,
		"FileSource": "Digital Camera",
		"Flash": "No Flash",
		"FlashpixVersion": "0100",
		"ISO": 100,
		"ImageDescription": "Exif JPEG",
		"ImageHeight": 8,
		"ImageSize": "8x8",
		"ImageWidth": 8,
		"InteropIndex": "R98 - DCF basic file (sRGB)",
		"InteropVersion": "0100",
		"LightSource": "Unknown",
		"LightValue": 7.7,
		"Make": "LEGEND",
		"MaxApertureValue": 2.9,
		"MeteringMode": "Multi-segment",
		"Model": "SOSHOW730",
		"ModifyDate": "2001:01:01 00:32:15",
		"Orientation": "Horizontal (normal)",
		"PrintIMVersion": "0100",
		"ResolutionUnit": "inches",
		"ShutterSpeed": "1/14",
		"ShutterSpeedValue": "1/14",
		"Software": "SOSHOW730  V1.00",
		"ThumbnailImage": "(Binary data 5820 bytes)",
		"ThumbnailLength": 5820,
		"ThumbnailOffset": 864,
		"XResolution": 72,
		"YCbCrPositioning": "Co-sited",
		"YCbCrSubSampling": "YCbCr4:2:0 (2 2)",
		"YResolution": 72
	}
}