[
	{
		"img": "sampleImages/VistaQuest/VistaQuestVQ2110.jpg",
		"exifJS": {
			"Make": "ViewQuest              ",
			"Model": "VQ-2110                              ",
			"Orientation": 1,
			"XResolution": 72,
			"YResolution": 72,
			"ResolutionUnit": 2,
			"Software": "Ver 1.0\u0000\u0000\u0000\u0000\u0000\u0000\u0000\u0000\u0000\u0000\u0000\u0000\u0000\u0000\u0000\u0000",
			"DateTime": "2003:04:15 21:23:06",
			"YCbCrPositioning": 1,
			"ExifIFDPointer": 318,
			"undefined": [
				80,
				114,
				105,
				110,
				116,
				73,
				77,
				0,
				48,
				50,
				53,
				48,
				0,
				0,
				0,
				4,
				0,
				2,
				1,
				0,
				0,
				0,
				0,
				14,
				0,
				0,
				1,
				52,
				1,
				0,
				5,
				0,
				0,
				0,
				1,
				1,
				1,
				0,
				0,
				0,
				0,
				0,
				0,
				0,
				0,
				0,
				0,
				0,
				0
			],
			"ExposureTime": 0.004651162790697674,
			"FNumber": 3.3,
			"ExposureProgram": "Normal program",
			"ISOSpeedRatings": 100,
			"ExifVersion": "0220",
			"DateTimeOriginal": "2003:04:15 21:23:06",
			"DateTimeDigitized": "2003:04:15 21:23:06",
			"ComponentsConfiguration": "YCbCr",
			"CompressedBitsPerPixel": 3.638716666666667,
			"ExposureBias": 0,
			"MaxApertureValue": 6,
			"MeteringMode": "CenterWeightedAverage",
			"Flash": "Flash did not fire",
			"FocalLength": 6.21,
			"MakerNote": [
				0,
				14,
				0,
				2,
				0,
				3,
				0,
				0,
				0,
				1,
				0,
				3,
				0,
				0,
				0,
				3,
				0,
				3,
				0,
				0,
				0,
				1,
				0,
				1,
				0,
				0,
				0,
				4,
				0,
				3,
				0,
				0,
				0,
				1,
				0,
				1,
				0,
				0,
				0,
				7,
				0,
				3,
				0,
				0,
				0,
				1,
				0,
				1,
				0,
				0,
				0,
				10,
				0,
				4,
				0,
				0,
				0,
				1,
				0,
				1,
				0,
				0,
				0,
				16,
				0,
				3,
				0,
				0,
				0,
				1,
				0,
				0,
				0,
				0,
				0,
				17,
				0,
				4,
				0,
				0,
				0,
				1,
				0,
				104,
				0,
				81,
				0,
				18,
				0,
				3,
				0,
				0,
				0,
				1,
				0,
				108,
				0,
				0,
				0,
				19,
				0,
				3,
				0,
				0,
				0,
				1,
				0,
				16,
				0,
				0,
				0,
				21,
				0,
				2,
				0,
				0,
				0,
				18,
				0,
				0,
				3,
				70,
				0,
				25,
				0,
				3,
				0,
				0,
				0,
				1,
				0,
				1,
				0,
				0,
				0,
				28,
				0,
				3,
				0,
				0,
				0,
				1,
				0,
				1,
				0,
				0,
				0,
				29,
				0,
				3,
				0,
				0,
				0,
				1,
				0,
				1,
				0,
				0,
				14,
				0,
				0,
				7,
				0,
				0,
				0,
				52,
				0,
				0,
				0,
				34,
				0,
				0,
				0,
				0,
				48,
				48,
				49,
				50,
				0,
				0,
				51,
				49,
				49,
				52,
				0,
				0,
				51,
				52,
				53,
				54,
				0,
				0,
				80,
				114,
				105,
				110,
				116,
				73,
				77,
				0,
				48,
				49,
				48,
				48,
				0,
				0,
				0,
				4,
				0,
				2,
				1,
				0,
				0,
				0,
				0,
				14,
				0,
				0,
				0,
				74,
				1,
				0,
				5,
				0,
				0,
				0,
				1,
				1,
				1,
				0,
				0,
				0,
				0,
				0,
				0,
				0,
				0,
				0,
				0,
				0,
				0,
				0,
				0,
				0,
				0,
				0,
				0,
				0,
				0,
				0,
				0,
				0,
				0,
				0,
				0,
				0
			],
			"FlashpixVersion": "0100",
			"ColorSpace": 1,
			"PixelXDimension": 1600,
			"PixelYDimension": 1200,
			"InteroperabilityIFDPointer": 920,
			"FileSource": "DSC"
		},
		"exifPerl": {
			"SourceFile": "sampleImages/VistaQuest/VistaQuestVQ2110.jpg",
			"ExifToolVersion": 9.41,
			"FileName": "VistaQuestVQ2110.jpg",
			"Directory": "sampleImages/VistaQuest",
			"FileSize": "16 kB",
			"FileModifyDate": "2013:07:31 12:29:09+01:00",
			"FileAccessDate": "2014:04:04 17:58:06+01:00",
			"FileInodeChangeDate": "2014:04:04 12:31:49+01:00",
			"FilePermissions": "rwxr-xr-x",
			"FileType": "JPEG",
			"MIMEType": "image/jpeg",
			"ExifByteOrder": "Big-endian (Motorola, MM)",
			"Make": "ViewQuest",
			"Model": "VQ-2110",
			"Orientation": "Horizontal (normal)",
			"XResolution": 72,
			"YResolution": 72,
			"ResolutionUnit": "inches",
			"Software": "Ver 1.0",
			"ModifyDate": "2003:04:15 21:23:06",
			"YCbCrPositioning": "Centered",
			"ExposureTime": "1/215",
			"FNumber": 3.3,
			"ExposureProgram": "Program AE",
			"ISO": 100,
			"ExifVersion": "0220",
			"DateTimeOriginal": "2003:04:15 21:23:06",
			"CreateDate": "2003:04:15 21:23:06",
			"ComponentsConfiguration": "Y, Cb, Cr, -",
			"CompressedBitsPerPixel": 3.638716667,
			"ExposureCompensation": 0,
			"MaxApertureValue": 8,
			"MeteringMode": "Center-weighted average",
			"Flash": "No Flash",
			"FocalLength": "6.2 mm",
			"Warning": "Invalid PrintIM header",
			"FlashpixVersion": "0100",
			"ColorSpace": "sRGB",
			"ExifImageWidth": 1600,
			"ExifImageHeight": 1200,
			"InteropIndex": "R98 - DCF basic file (sRGB)",
			"InteropVersion": "0100",
			"FileSource": "Digital Camera",
			"PrintIMVersion": "0250",
			"Compression": "JPEG (old-style)",
			"ThumbnailOffset": 1057,
			"ThumbnailLength": 14944,
			"ImageWidth": 8,
			"ImageHeight": 8,
			"EncodingProcess": "Baseline DCT, Huffman coding",
			"BitsPerSample": 8,
			"ColorComponents": 3,
			"YCbCrSubSampling": "YCbCr4:2:0 (2 2)",
			"Aperture": 3.3,
			"ImageSize": "8x8",
			"ShutterSpeed": "1/215",
			"ThumbnailImage": "(Binary data 14944 bytes)",
			"FocalLength35efl": "6.2 mm",
			"LightValue": 11.2
		}
	},
	{
		"img": "sampleImages/VistaQuest/VistaQuestVQ1015.jpg",
		"exifJS": {},
		"exifPerl": {
			"SourceFile": "sampleImages/VistaQuest/VistaQuestVQ1015.jpg",
			"ExifToolVersion": 9.41,
			"FileName": "VistaQuestVQ1015.jpg",
			"Directory": "sampleImages/VistaQuest",
			"FileSize": "3.3 kB",
			"FileModifyDate": "2013:07:31 12:29:09+01:00",
			"FileAccessDate": "2014:04:04 17:58:06+01:00",
			"FileInodeChangeDate": "2014:04:04 12:31:49+01:00",
			"FilePermissions": "rwxr-xr-x",
			"FileType": "JPEG",
			"MIMEType": "image/jpeg",
			"ExifByteOrder": "Little-endian (Intel, II)",
			"Make": "VISTAQUEST",
			"Model": "VQ1015",
			"Orientation": "Horizontal (normal)",
			"XResolution": 72,
			"YResolution": 72,
			"ResolutionUnit": "inches",
			"ModifyDate": "2010:03:16 11:02:52",
			"YCbCrPositioning": "Co-sited",
			"ExposureTime": "1/5",
			"FNumber": 2.8,
			"ISO": 60,
			"ExifVersion": "0210",
			"DateTimeOriginal": "2010:03:16 11:02:52",
			"CreateDate": "2010:03:16 11:02:52",
			"ComponentsConfiguration": "Y, Cb, Cr, -",
			"CompressedBitsPerPixel": 2,
			"MeteringMode": "Center-weighted average",
			"Flash": "No Flash",
			"FlashpixVersion": "0100",
			"ColorSpace": "sRGB",
			"ExifImageWidth": 1280,
			"ExifImageHeight": 1024,
			"FileSource": "Digital Camera",
			"SceneType": "Directly photographed",
			"Compression": "JPEG (old-style)",
			"ThumbnailOffset": 691,
			"ThumbnailLength": 2363,
			"ImageWidth": 8,
			"ImageHeight": 8,
			"EncodingProcess": "Baseline DCT, Huffman coding",
			"BitsPerSample": 8,
			"ColorComponents": 3,
			"YCbCrSubSampling": "YCbCr4:2:0 (2 2)",
			"Aperture": 2.8,
			"ImageSize": "8x8",
			"ShutterSpeed": "1/5",
			"ThumbnailImage": "(Binary data 2363 bytes)",
			"LightValue": 6
		}
	}
]