{
	"img": "sampleImages/Samsung/SamsungD250DigitalCAM.jpg",
	"exifJS": {
		"BrightnessValue": "10.099",
		"ColorSpace": "sRGB",
		"ComponentsConfiguration": "Y, Cb, Cr, -",
		"CompressedBitsPerPixel": "1.96565",
		"Contrast": "Normal",
		"CustomRendered": "Normal",
		"DateTime": "2013:10:01 21:44:53",
		"DateTimeDigitized": "2013:10:01 21:44:51",
		"DateTimeOriginal": "2013:10:01 21:44:51",
		"DigitalZoomRatio": "1",
		"ExifIFDPointer": "332",
		"ExifVersion": "0220",
		"ExposureBias": "0",
		"ExposureMode": "0",
		"ExposureProgram": "Normal program",
		"ExposureTime": "0.0024813895781637717",
		"FNumber": "6.668",
		"FileSource": "DSC",
		"Flash": "No Flash",
		"FlashpixVersion": "0100",
		"FocalLength": "5 mm",
		"FocalLengthIn35mmFilm": "0",
		"GainControl": "Low gain up",
		"ISOSpeedRatings": "70",
		"ImageDescription": "S2500015.JPG",
		"InteroperabilityIFDPointer": "1518",
		"LightSource": "",
		"Make": "SAMSUNG",
		"MakerNoteIFDPointer": "778",
		"MaxApertureValue": "3.4",
		"MeteringMode": "MultiSpot",
		"Model": "D250 DigitalCAM",
		"Orientation": "1",
		"PixelXDimension": "800",
		"PixelYDimension": "600",
		"ResolutionUnit": "2",
		"Saturation": "Normal",
		"SceneCaptureType": "Standard",
		"SceneType": "Directly photographed",
		"Sharpness": "Soft",
		"Software": "01011.0",
		"SubjectArea": "0,0",
		"SubjectDistanceRange": "Distant view",
		"WhiteBalance": "",
		"XResolution": "72",
		"YCbCrPositioning": "2",
		"YResolution": "72"
	},
	"exifGomfunkel": {
		"BrightnessValue": 10.099,
		"ColorSpace": 1,
		"CompressedBitsPerPixel": 1.96565,
		"Compression": 6,
		"Contrast": 0,
		"CreateDate": "2013:10:01 21:44:51",
		"CustomRendered": 0,
		"DateTimeOriginal": "2013:10:01 21:44:51",
		"DigitalZoomRatio": 1,
		"ExifImageHeight": 600,
		"ExifImageWidth": 800,
		"ExifOffset": 332,
		"ExposureCompensation": 0,
		"ExposureMode": 0,
		"ExposureProgram": 2,
		"ExposureTime": 0.0024813895781637717,
		"FNumber": 6.668,
		"Flash": 0,
		"FocalLength": 5,
		"FocalLengthIn35mmFormat": 0,
		"GainControl": 1,
		"ISO": 70,
		"ImageDescription": "S2500015.JPG                   ",
		"InteropIndex": "R98",
		"InteropOffset": 1518,
		"LightSource": 0,
		"Make": "SAMSUNG                      ",
		"MaxApertureValue": 3.4,
		"MeteringMode": 4,
		"Model": "D250 DigitalCAM",
		"ModifyDate": "2013:10:01 21:44:53",
		"Orientation": 1,
		"ResolutionUnit": 2,
		"Saturation": 0,
		"SceneCaptureType": 0,
		"Sharpness": 1,
		"Software": "01011.0",
		"SubjectArea": [
			0,
			0
		],
		"SubjectDistanceRange": 3,
		"ThumbnailLength": 1381,
		"ThumbnailOffset": 1548,
		"WhiteBalance": 6,
		"XResolution": 72,
		"YCbCrPositioning": 2,
		"YResolution": 72,
		"error": "Unable to extract Makernote information as it is in an unsupported or unrecognized format."
	},
	"exifPerl": {
		"Aperture": 6.7,
		"BitsPerSample": 8,
		"BrightnessValue": 10.099,
		"ColorComponents": 3,
		"ColorSpace": "sRGB",
		"ComponentsConfiguration": "Y, Cb, Cr, -",
		"CompressedBitsPerPixel": 1.96565,
		"Compression": "JPEG (old-style)",
		"Contrast": "Normal",
		"CreateDate": "2013:10:01 21:44:51",
		"CustomRendered": "Normal",
		"DateTimeOriginal": "2013:10:01 21:44:51",
		"DigitalZoomRatio": 1,
		"EncodingProcess": "Baseline DCT, Huffman coding",
		"ExifByteOrder": "Little-endian (Intel, II)",
		"ExifImageHeight": 600,
		"ExifImageWidth": 800,
		"ExifVersion": "0220",
		"ExposureCompensation": 0,
		"ExposureMode": "Auto",
		"ExposureProgram": "Program AE",
		"ExposureTime": "1/403",
		"FNumber": 6.7,
		"FileSource": "Digital Camera",
		"Flash": "No Flash",
		"FlashpixVersion": "0100",
		"FocalLength": "5.0 mm",
		"FocalLength35efl": "5.0 mm",
		"FocalLengthIn35mmFormat": "0 mm",
		"GainControl": "Low gain up",
		"ISO": 70,
		"ImageDescription": "S2500015.JPG                   ",
		"ImageHeight": 8,
		"ImageSize": "8x8",
		"ImageWidth": 8,
		"InteropIndex": "R98 - DCF basic file (sRGB)",
		"InteropVersion": "0101",
		"JFIFVersion": 1.01,
		"LightSource": "Unknown",
		"LightValue": 14.6,
		"Make": "SAMSUNG",
		"MaxApertureValue": 3.2,
		"MeteringMode": "Multi-spot",
		"Model": "D250 DigitalCAM",
		"ModifyDate": "2013:10:01 21:44:53",
		"Orientation": "Horizontal (normal)",
		"PrintIMVersion": "0250",
		"ResolutionUnit": "inches",
		"Saturation": "Normal",
		"SceneCaptureType": "Standard",
		"SceneType": "Directly photographed",
		"Sharpness": "Soft",
		"ShutterSpeed": "1/403",
		"Software": "01011.0",
		"SubjectArea": "0 0",
		"SubjectDistanceRange": "Distant",
		"ThumbnailImage": "(Binary data 1381 bytes)",
		"ThumbnailLength": 1381,
		"ThumbnailOffset": 1578,
		"Warning": "[minor] Unrecognized MakerNotes",
		"WhiteBalance": "Unknown (6)",
		"XResolution": 72,
		"YCbCrPositioning": "Co-sited",
		"YCbCrSubSampling": "YCbCr4:2:0 (2 2)",
		"YResolution": 72
	}
}