{
	"img": "sampleImages/Sony/SonyDSC-TX100.jpg",
	"exifJS": {
		"BrightnessValue": "1.196875",
		"ColorSpace": "sRGB",
		"ComponentsConfiguration": "Y, Cb, Cr, -",
		"CompressedBitsPerPixel": "1",
		"Contrast": "Normal",
		"CustomRendered": "Normal",
		"DateTime": "2011:08:18 00:55:19",
		"DateTimeDigitized": "2011:08:18 00:55:19",
		"DateTimeOriginal": "2011:08:18 00:55:19",
		"DigitalZoomRatio": "1",
		"ExifIFDPointer": "272",
		"ExifVersion": "0230",
		"ExposureBias": "0",
		"ExposureMode": "0",
		"ExposureProgram": "Normal program",
		"ExposureTime": "0.03333333333333333",
		"FNumber": "3.5",
		"FileSource": "DSC",
		"Flash": "Flash fired, auto mode, return light detected",
		"FlashpixVersion": "0100",
		"FocalLength": "4.43 mm",
		"ISOSpeedRatings": "200",
		"ImageDescription": "",
		"InteroperabilityIFDPointer": "13242",
		"LightSource": "",
		"Make": "SONY",
		"MakerNoteIFDPointer": "806",
		"MaxApertureValue": "3.625",
		"MeteringMode": "Pattern",
		"Model": "DSC-TX100",
		"Orientation": "1",
		"PixelXDimension": "4608",
		"PixelYDimension": "3456",
		"ResolutionUnit": "2",
		"Saturation": "Normal",
		"SceneCaptureType": "Standard",
		"SceneType": "Directly photographed",
		"Sharpness": "Normal",
		"UserComment": "13138",
		"WhiteBalance": "Auto",
		"XResolution": "72",
		"YCbCrPositioning": "2",
		"YResolution": "72"
	},
	"exifGomfunkel": {
		"BrightnessValue": 1.196875,
		"ColorSpace": 1,
		"CompressedBitsPerPixel": 1,
		"Compression": 6,
		"Contrast": 0,
		"CreateDate": "2011:08:18 00:55:19",
		"CustomRendered": 0,
		"DateTimeOriginal": "2011:08:18 00:55:19",
		"DigitalZoomRatio": 1,
		"ExifImageHeight": 3456,
		"ExifImageWidth": 4608,
		"ExifOffset": 272,
		"ExposureCompensation": 0,
		"ExposureMode": 0,
		"ExposureProgram": 2,
		"ExposureTime": 0.03333333333333333,
		"FNumber": 3.5,
		"Flash": 31,
		"FocalLength": 4.43,
		"ISO": 200,
		"ImageDescription": "                               ",
		"InteropIndex": "R98",
		"InteropOffset": 13242,
		"LensInfo": [
			4.43,
			17.7,
			3.5,
			4.6
		],
		"LightSource": 0,
		"Make": "SONY",
		"MaxApertureValue": 3.625,
		"MeteringMode": 5,
		"Model": "DSC-TX100              ",
		"ModifyDate": "2011:08:18 00:55:19",
		"Orientation": 1,
		"RecommendedExposureIndex": 200,
		"ResolutionUnit": 2,
		"Saturation": 0,
		"SceneCaptureType": 0,
		"SensitivityType": 2,
		"Sharpness": 0,
		"ThumbnailLength": 8918,
		"ThumbnailOffset": 13520,
		"WhiteBalance": 0,
		"XResolution": 72,
		"YCbCrPositioning": 2,
		"YResolution": 72,
		"error": "Unable to extract Makernote information as it is in an unsupported or unrecognized format."
	},
	"exifPerl": {
		"AFAreaMode": "Multi",
		"AFIlluminator": "Auto",
		"Anti-Blur": "On (Shooting)",
		"Aperture": 3.5,
		"BitsPerSample": 8,
		"Brightness": 0,
		"BrightnessValue": 1.196875,
		"CameraOrientation": "Horizontal (normal)",
		"CameraTemperature": "35 C",
		"ColorComponents": 3,
		"ColorSpace": "sRGB",
		"ComponentsConfiguration": "Y, Cb, Cr, -",
		"CompressedBitsPerPixel": 1,
		"Compression": "JPEG (old-style)",
		"Contrast": "Normal",
		"CreateDate": "2011:08:18 00:55:19",
		"CreativeStyle": "Standard",
		"CustomRendered": "Normal",
		"DateTimeOriginal": "2011:08:18 00:55:19",
		"DependentImage1EntryNumber": 0,
		"DependentImage2EntryNumber": 0,
		"DigitalZoom": "No",
		"DigitalZoomRatio": 1,
		"DynamicRangeOptimizer": "Standard",
		"EncodingProcess": "Baseline DCT, Huffman coding",
		"ExifByteOrder": "Little-endian (Intel, II)",
		"ExifImageHeight": 3456,
		"ExifImageWidth": 4608,
		"ExifVersion": "0230",
		"ExposureCompensation": 0,
		"ExposureMode": "Auto",
		"ExposureProgram": "Program AE",
		"ExposureTime": "1/30",
		"FNumber": 3.5,
		"Face1Position": "1354 1973 749 749",
		"Face2Position": "1397 648 691 691",
		"Face3Position": "1598 3470 461 461",
		"FaceInfoLength": 37,
		"FaceInfoOffset": 94,
		"FacesDetected": 3,
		"FileSource": "Digital Camera",
		"Flash": "Auto, Fired, Return detected",
		"FlashLevel": "n/a",
		"FlashpixVersion": "0100",
		"FocalLength": "4.4 mm",
		"FocalLength35efl": "4.4 mm",
		"FocusMode": "AF-S",
		"HDR": "Off; Uncorrected image",
		"HighISONoiseReduction": "n/a",
		"HighISONoiseReduction2": "Low",
		"ISO": 200,
		"ImageDescription": "                               ",
		"ImageHeight": 8,
		"ImageSize": "8x8",
		"ImageStabilization": "On",
		"ImageWidth": 8,
		"IntelligentAuto": "On",
		"InteropIndex": "R98 - DCF basic file (sRGB)",
		"InteropVersion": "0100",
		"JPEGQuality": "Standard",
		"LensInfo": "4.43-17.7mm f/3.5-4.6",
		"LightSource": "Unknown",
		"LightValue": 7.5,
		"LongExposureNoiseReduction": "n/a",
		"MPFVersion": "0100",
		"MPImageFlags": "Dependent child image",
		"MPImageFormat": "JPEG",
		"MPImageLength": 294676,
		"MPImageStart": 2447872,
		"MPImageType": "Large Thumbnail (full HD equivalent)",
		"Macro": "Off",
		"Make": "SONY",
		"MaxApertureValue": 3.5,
		"MetaVersion": "DC7303320222000",
		"MeteringMode": "Multi-segment",
		"Model": "DSC-TX100",
		"ModifyDate": "2011:08:18 00:55:19",
		"NumberOfImages": 2,
		"Orientation": "Horizontal (normal)",
		"PreviewImage": "(Binary data 294676 bytes)",
		"PrintIMVersion": "0300",
		"Quality2": "JPEG",
		"Rating": 0,
		"RecommendedExposureIndex": 200,
		"ReleaseMode": "Normal",
		"ReleaseMode2": "Normal",
		"ResolutionUnit": "inches",
		"Saturation": "Normal",
		"SceneCaptureType": "Standard",
		"SceneMode": "n/a",
		"SceneType": "Directly photographed",
		"SensitivityType": "Recommended Exposure Index",
		"SequenceFileNumber": 1,
		"SequenceImageNumber": 1,
		"SequenceLength": "1 shot",
		"SequenceNumber": "Single",
		"Sharpness": "Normal",
		"ShotNumberSincePowerUp": 3,
		"ShutterSpeed": "1/30",
		"SonyDateTime": "2011:08:18 00:55:19",
		"SonyImageHeight": 3456,
		"SonyImageWidth": 4608,
		"ThumbnailImage": "(Binary data 8918 bytes)",
		"ThumbnailLength": 8918,
		"ThumbnailOffset": 13532,
		"UserComment": "",
		"WhiteBalance": "Auto",
		"XResolution": 72,
		"YCbCrPositioning": "Co-sited",
		"YCbCrSubSampling": "YCbCr4:2:0 (2 2)",
		"YResolution": 72,
		"ZoneMatching": "ISO Setting Used"
	}
}