{
	"ImageDescription": "M3321T-0015",
	"Make": "TRUST",
	"Model": "962Z POWER",
	"Orientation": 1,
	"XResolution": 72,
	"YResolution": 72,
	"ModifyDate": "2005:01:12 13:26:25",
	"YCbCrPositioning": 2,
	"ExifOffset": 205,
	"Compression": 6,
	"ThumbnailOffset": 737,
	"ThumbnailLength": 4378,
	"ExposureTime": "1/125",
	"FNumber": 5.6,
	"ISO": 100,
	"ExifVersion": "2.1",
	"DateTimeOriginal": "2005:01:12 13:26:25",
	"CreateDate": "2005:01:12 13:26:25",
	"CompressedBitsPerPixel": 2,
	"FlashpixVersion": "1",
	"ExifImageWidth": 2272,
	"ExifImageHeight": 1704,
	"RelatedSoundFile": "",
	"InteropOffset": 589,
	"InteropIndex": "R98",
	"InteropVersion": "1"
}