{
	"ColorSpace": "sRGB",
	"ComponentsConfiguration": "Y, Cb, Cr, -",
	"Contrast": "Normal",
	"CreateDate": "2008:06:23 17:52:35",
	"CustomRendered": "Normal",
	"DateTimeOriginal": "2008:06:23 17:52:35",
	"DigitalZoomRatio": "1",
	"ExifIFDPointer": "250",
	"ExifImageHeight": "2304",
	"ExifImageWidth": "3072",
	"ExifVersion": "0220",
	"ExposureBias": "0",
	"ExposureMode": "0",
	"ExposureProgram": "Landscape mode",
	"ExposureTime": "0.003097",
	"FNumber": "5.6",
	"FileSource": "DSC",
	"Flash": "Flash did not fire, compulsory flash mode",
	"FlashpixVersion": "0100",
	"FocalLength": "5.5 mm",
	"GainControl": "Low gain up",
	"ISO": "80",
	"ImageDescription": "PENTAX Image",
	"InteroperabilityIFDPointer": "9270",
	"Make": "PENTAX Corporation",
	"MakerNoteIFDPointer": "684",
	"MaxApertureValue": "3",
	"MeteringMode": "Spot",
	"Model": "PENTAX OptioE25",
	"ModifyDate": "2008:06:23 17:52:35",
	"Orientation": "1",
	"ResolutionUnit": "2",
	"Saturation": "High saturation",
	"SceneCaptureType": "Landscape",
	"Sharpness": "Normal",
	"Software": "V1.00",
	"WhiteBalance": "Manual",
	"XResolution": "314",
	"YCbCrPositioning": "1",
	"YResolution": "314"
}