{
	"Compression": 6,
	"Make": "SAMSUNG",
	"Model": "GT-B3410",
	"Orientation": 1,
	"XResolution": 72,
	"YResolution": 72,
	"ResolutionUnit": 2,
	"YCbCrPositioning": 1,
	"ExifOffset": 155,
	"DateTimeOriginal": "2010:07:29 21:20:30",
	"CreateDate": "2010:07:29 21:20:30",
	"ColorSpace": 1,
	"ExifImageWidth": 640,
	"ExifImageHeight": 480,
	"ExposureTime": 0.029411764705882353,
	"FNumber": 2.8,
	"ExposureProgram": 3,
	"MaxApertureValue": 3,
	"MeteringMode": 2,
	"Flash": 0,
	"FocalLength": 3.72,
	"ExposureMode": 0,
	"WhiteBalance": 0,
	"SceneCaptureType": 3,
	"InteropOffset": 461,
	"InteropIndex": "R98"
}