{
	"ApertureValue": "6.5",
	"ColorSpace": "sRGB",
	"ComponentsConfiguration": "Y, Cb, Cr, -",
	"Contrast": "Normal",
	"CustomRendered": "Normal",
	"DateTimeDigitized": "2009:11:12 10:31:25",
	"DateTimeOriginal": "2009:11:12 10:31:25",
	"DigitalZoomRatio": "0",
	"ExifIFDPointer": "300",
	"ExifVersion": "0220",
	"ExposureBias": "-1",
	"ExposureProgram": "Aperture priority",
	"ExposureTime": "0.011111111111111112",
	"FileSource": "DSC",
	"Flash": "No Flash",
	"FocalLength": "70 mm",
	"ISOSpeedRatings": "160",
	"ImageUniqueID": "00000000000000000000000003566061",
	"LightSource": "",
	"Make": "Leica Camera AG",
	"MakerNoteIFDPointer": "15294073",
	"MaxApertureValue": "2.640625",
	"MeteringMode": "MultiSpot",
	"Model": "S2",
	"Orientation": "1",
	"PixelXDimension": "7488",
	"PixelYDimension": "4976",
	"ResolutionUnit": "2",
	"Saturation": "Normal",
	"SceneCaptureType": "Standard",
	"SceneType": "Directly photographed",
	"Sharpness": "Normal",
	"ShutterSpeedValue": "6.47265625",
	"Software": "1.0.0.9",
	"WhiteBalance": "Auto",
	"XResolution": "300",
	"YCbCrPositioning": "2",
	"YCbCrSubSampling": "2,1",
	"YResolution": "300"
}